gavagai/__init__.py
gavagai/client.py
gavagai/exceptions.py
gavagai-0.2.3.dist-info/DESCRIPTION.rst
gavagai-0.2.3.dist-info/METADATA
gavagai-0.2.3.dist-info/metadata.json
gavagai-0.2.3.dist-info/RECORD
gavagai-0.2.3.dist-info/top_level.txt
gavagai-0.2.3.dist-info/WHEEL
