Metadata-Version: 2.0
Name: gavagai
Version: 0.2.3
Summary: A Gavagai API helper library.
Home-page: https://github.com/dewe/gavagai-python
Author: Johan Dewe
Author-email: johan@dewe.net
License: The MIT License (MIT)
Keywords: text-analysis,api,nlp
Platform: UNKNOWN
Requires-Dist: requests (>=2.7.0,<3.0)
Requires-Dist: urllib3
Requires-Dist: ndg-httpsclient
